{"dataURL":"file:\/\/\/Users\/attie\/Desktop\/Training%20Data\/","id":"9B76FE17-8569-43BF-91F2-D46E816B0C93","createdDate":"2022-06-04T16:52:04Z","title":"Training Data","modifiedDate":"2022-06-04T16:52:09Z","preferredFilename":"Training Data","version":"1.0","dataResult":{"dataURL":"file:\/\/\/Users\/attie\/Desktop\/Training%20Data\/","createdDate":"2022-06-04T16:52:04Z","dataSourceID":"9B76FE17-8569-43BF-91F2-D46E816B0C93"},"activityEntities":["dataSourceCreated",[{"id":"3F6A29F4-D5A8-4A78-B8D1-615024B8EDBE","title":"Data Source Created","createdDate":"2022-06-04T16:52:04Z","event":"dataSourceCreated","subtitle":"Training Data"}],"dataSourceMetrics",[{"id":"96B61221-3FDE-417B-B0FB-DA23659F8121","title":"Data Summary","createdDate":"2022-06-04T16:52:09Z","event":"dataSourceMetrics","subtitle":"2 Classes, 87 Items"}],"dataSourceTrainingStarted",[{"id":"77EDC323-C2AE-4F15-9154-F66041E7EF9F","title":"Used By","createdDate":"2022-06-04T16:52:09Z","event":"dataSourceTrainingStarted","subtitle":"MyImageClassifier 1"}]],"pathType":0,"experimentIDs":["FA3859EA-9354-4479-988E-3C483B7C9D20"]}